zsm_lib/__init__.py
zsm_lib/config.py
zsm_lib/manage.py
zsm_lib/zfs.py
zsm_lib-0.2.1.dist-info/LICENSE
zsm_lib-0.2.1.dist-info/METADATA
zsm_lib-0.2.1.dist-info/WHEEL
zsm_lib-0.2.1.dist-info/top_level.txt
zsm_lib-0.2.1.dist-info/RECORD
