Metadata-Version: 2.1
Name: zsm-lib
Version: 0.2.1
Summary: ZFS Snapshot Manager Library
Home-page: UNKNOWN
Author: Mattias Lindvall
Author-email: mattias.lindvall@gmail.com
License: BSD-2-Clause
Project-URL: Documentation, https://zsm.readthedocs.io/
Project-URL: Source, https://gitlab.com/thnee/zsm-lib
Keywords: zfs snapshots freebsd linux library
Platform: UNKNOWN
Classifier: Development Status :: 3 - Alpha
Classifier: Intended Audience :: Developers
Classifier: Operating System :: POSIX :: BSD :: FreeBSD
Classifier: Operating System :: POSIX :: Linux
Classifier: Programming Language :: Python
Classifier: Programming Language :: Python :: 3
Classifier: Programming Language :: Python :: 3.6
Classifier: Programming Language :: Python :: 3.7
Classifier: Programming Language :: Python :: 3.8
Classifier: Programming Language :: Python :: 3 :: Only
Classifier: Topic :: System :: Filesystems
Classifier: Topic :: Software Development :: Libraries :: Python Modules
Requires-Python: >=3.6
Requires-Dist: sarge (~=0.1.6)
Requires-Dist: pyyaml (~=5.4.1)
Requires-Dist: marshmallow (~=3.10.0)
